AL_Khatma/__init__.py
AL_Khatma/adkar.py
AL_Khatma/cheak.py
AL_Khatma/khatma.py
AL_Khatma/log.py
AL_Khatma/message.py
AL_Khatma/pdf_page.py
AL_Khatma/quran.py
AL_Khatma/tafser.py
AL_Khatma_lib-2.0.3.dist-info/LICENSE
AL_Khatma_lib-2.0.3.dist-info/METADATA
AL_Khatma_lib-2.0.3.dist-info/WHEEL
AL_Khatma_lib-2.0.3.dist-info/top_level.txt
AL_Khatma_lib-2.0.3.dist-info/RECORD
