Metadata-Version: 2.1
Name: AL_Khatma_lib
Version: 2.0.3
Summary: A library Specialized About Islamic
Author-email: Osamah Awadh <osamahawadh01@gmail.com>
Project-URL: Homepage, https://github.com/oaokm/AL-Khatma
Project-URL: Bug Tracker, https://github.com/oaokm/AL-Khatma/issues
Classifier: Programming Language :: Python :: 3
Classifier: License :: OSI Approved :: MIT License
Classifier: Operating System :: OS Independent
Requires-Python: >=3
License-File: LICENSE
